{"PillarName":"Economy","NSDPIndicatorID":"ECO 3.1.2","IndicatorShortName":"Business Participation in Annual Agri-Tourism Festival ","graph_type":"bar","data_non_statistical":false,"graph_title":"Number of businesses participating in the annual agri-tourism festival by sector","indicator_number":"ECO3-1-2","goal_number":"ECO3","goal_name":"global_goals.ECO3-title","target_number":"ECO3-1","target_name":"global_targets.ECO3-1-title","indicator_name":"indicators.ECO3-1-2-title","national_geographical_coverage":"Vanuatu","indicator":"ECO3.1.2","target_id":"ECO3.1","sdg_goal":"ECO3","reporting_status":"notstarted","indicator_sort_order":"ECO3-01-02"}