{"PillarName":"Environment","NSDPIndicatorID":"ENV 1.4.2","IndicatorShortName":"Food Storage and Preservation Trainings","graph_type":"bar","data_non_statistical":false,"graph_title":"Total number of people receiving training in food storage and preservation per year in MALFFB led, NGO or partnered initiatives","indicator_number":"ENV1-4-2","goal_number":"ENV1","goal_name":"global_goals.ENV1-title","target_number":"ENV1-4","target_name":"global_targets.ENV1-4-title","indicator_name":"indicators.ENV1-4-2-title","national_geographical_coverage":"Vanuatu","indicator":"ENV1.4.2","target_id":"ENV1.4","sdg_goal":"ENV1","reporting_status":"notstarted","indicator_sort_order":"ENV1-04-02"}